four_k_search_engine_nosrednakram/FilterList.py
four_k_search_engine_nosrednakram/FilterSet.py
four_k_search_engine_nosrednakram/IndexListCompare.py
four_k_search_engine_nosrednakram/LoadSearchData.py
four_k_search_engine_nosrednakram/Search.py
four_k_search_engine_nosrednakram/__init__.py
four_k_search_engine-0.1.1.dist-info/LICENSE
four_k_search_engine-0.1.1.dist-info/WHEEL
four_k_search_engine-0.1.1.dist-info/METADATA
four_k_search_engine-0.1.1.dist-info/RECORD
