Metadata-Version: 2.3
Name: four_k_search_engine
Version: 0.1.1
Summary: Simple search engine for a list of dictionaries with search and filter.
Author-email: Mark W Anderson <nosrednakram@gmail.com>
Classifier: License :: OSI Approved :: MIT License
